odoo/addons/attachment_unindex_content/README.rst
odoo/addons/attachment_unindex_content/__init__.py
odoo/addons/attachment_unindex_content/__manifest__.py
odoo/addons/attachment_unindex_content/hooks.py
odoo/addons/attachment_unindex_content/i18n/attachment_unindex_content.pot
odoo/addons/attachment_unindex_content/i18n/tr.po
odoo/addons/attachment_unindex_content/models/__init__.py
odoo/addons/attachment_unindex_content/models/ir_attachment.py
odoo/addons/attachment_unindex_content/readme/CONTRIBUTORS.rst
odoo/addons/attachment_unindex_content/readme/DESCRIPTION.rst
odoo/addons/attachment_unindex_content/static/description/icon.png
odoo/addons/attachment_unindex_content/static/description/index.html
odoo12_addon_attachment_unindex_content-12.0.1.0.0.99.dev6.dist-info/METADATA
odoo12_addon_attachment_unindex_content-12.0.1.0.0.99.dev6.dist-info/WHEEL
odoo12_addon_attachment_unindex_content-12.0.1.0.0.99.dev6.dist-info/top_level.txt
odoo12_addon_attachment_unindex_content-12.0.1.0.0.99.dev6.dist-info/RECORD
